pendsim/__init__.py
pendsim/controller.py
pendsim/sim.py
pendsim/test_controller.py
pendsim/utils.py
pendsim/viz.py
pendsim-1.0.4.dist-info/LICENSE
pendsim-1.0.4.dist-info/METADATA
pendsim-1.0.4.dist-info/WHEEL
pendsim-1.0.4.dist-info/top_level.txt
pendsim-1.0.4.dist-info/RECORD
