Metadata-Version: 2.1
Name: pendsim
Version: 1.0.4
Summary: A pendulum simulator
Home-page: https://github.com/rland93/pendsim
Author: Mike Sutherland
Author-email: msutherl@uci.edu
License: MIT
Project-URL: Bug Tracker, https://github.com/rland93/pendsim/issues
Platform: UNKNOWN
Classifier: License :: OSI Approved :: MIT License
Classifier: Programming Language :: Python
Classifier: Programming Language :: Python :: 3
Classifier: Programming Language :: Python :: 3.6
Classifier: Programming Language :: Python :: Implementation :: CPython
Classifier: Programming Language :: Python :: Implementation :: PyPy
Requires-Python: >=3.6.0
License-File: LICENSE
Requires-Dist: matplotlib
Requires-Dist: six
Requires-Dist: scipy
Requires-Dist: numpy
Requires-Dist: pandas
Requires-Dist: tqdm
Requires-Dist: scikit-learn
Requires-Dist: pytest
Requires-Dist: filterpy
